pylsp_mypy_rnx/__init__.py
pylsp_mypy_rnx/plugin.py
pylsp_mypy_rnx-0.2.0.dist-info/entry_points.txt
pylsp_mypy_rnx-0.2.0.dist-info/LICENSE
pylsp_mypy_rnx-0.2.0.dist-info/WHEEL
pylsp_mypy_rnx-0.2.0.dist-info/METADATA
pylsp_mypy_rnx-0.2.0.dist-info/RECORD
