Metadata-Version: 2.1
Name: pylsp-mypy-rnx
Version: 0.2.0
Summary: mypy-ls fork
Home-page: https://github.com/gjeusel/pylsp-mypy-rnx
License: MIT
Keywords: lsp,mypy,python-lsp-server
Author: Guillaume Jeusel
Author-email: guillaume.jeusel@gmail.com
Requires-Python: >=3.7,<4.0
Classifier: Development Status :: 2 - Pre-Alpha
Classifier: Intended Audience :: Developers
Classifier: License :: OSI Approved :: MIT License
Classifier: Natural Language :: English
Classifier: Programming Language :: Python
Classifier: Programming Language :: Python :: 3
Classifier: Programming Language :: Python :: 3.7
Classifier: Programming Language :: Python :: 3.8
Classifier: Programming Language :: Python :: 3.9
Classifier: Programming Language :: Python :: 3.10
Classifier: Programming Language :: Python :: 3.8
Classifier: Programming Language :: Python :: 3.9
Classifier: Programming Language :: Python :: Implementation :: CPython
Classifier: Programming Language :: Python :: Implementation :: PyPy
Classifier: Topic :: Software Development
Requires-Dist: python-lsp-server (>=1.0,<2.0)
Requires-Dist: setuptools
Project-URL: Bug Tracker, https://github.com/gjeusel/pylsp-mypy-rnx/issues
Project-URL: Repository, https://github.com/gjeusel/pylsp-mypy-rnx
Project-URL: Source, https://github.com/gjeusel/pylsp-mypy-rnx
